pokepalette/__init__.py
pokepalette/_nbdev.py
pokepalette/core.py
pokepalette/pokemon_colours.json
pokepalette/pokemon_colours.py
pokepalette-0.0.6.dist-info/.ipynb_checkpoints/PKG-INFO-checkpoint
pokepalette-0.0.6.dist-info/.ipynb_checkpoints/SOURCES-checkpoint.txt
pokepalette-0.0.6.dist-info/.ipynb_checkpoints/dependency_links-checkpoint.txt
pokepalette-0.0.6.dist-info/.ipynb_checkpoints/entry_points-checkpoint.txt
pokepalette-0.0.6.dist-info/.ipynb_checkpoints/not-zip-safe-checkpoint
pokepalette-0.0.6.dist-info/.ipynb_checkpoints/requires-checkpoint.txt
pokepalette-0.0.6.dist-info/LICENSE
pokepalette-0.0.6.dist-info/METADATA
pokepalette-0.0.6.dist-info/WHEEL
pokepalette-0.0.6.dist-info/entry_points.txt
pokepalette-0.0.6.dist-info/top_level.txt
pokepalette-0.0.6.dist-info/RECORD
