Metadata-Version: 2.1
Name: pokepalette
Version: 0.0.6
Summary: A simple package to select you favourite pokemon colors
Home-page: https://github.com/tcapelle/pokepalette/tree/master/
Author: Thomas Capelle
Author-email: thomascapelle@gmail.com
License: Apache Software License 2.0
Keywords: python pokemon matplotlib
Platform: UNKNOWN
Classifier: Development Status :: 3 - Alpha
Classifier: Intended Audience :: Developers
Classifier: Natural Language :: English
Classifier: Programming Language :: Python :: 3.6
Classifier: Programming Language :: Python :: 3.7
Classifier: Programming Language :: Python :: 3.8
Classifier: License :: OSI Approved :: Apache Software License
Requires-Python: >=3.6
Requires-Dist: pip
Requires-Dist: packaging
Requires-Dist: matplotlib
Provides-Extra: dev
